bioblueprint/bioblueprint.py
bioblueprint/lib/__init__.py
bioblueprint/lib/graph.py
bioblueprint/lib/repos.py
bioblueprint/lib/wdl.py
bioblueprint/tools/__init__.py
bioblueprint/tools/update_io.py
bioblueprint-1.1.4.dist-info/licenses/LICENSE
bioblueprint-1.1.4.dist-info/METADATA
bioblueprint-1.1.4.dist-info/WHEEL
bioblueprint-1.1.4.dist-info/entry_points.txt
bioblueprint-1.1.4.dist-info/top_level.txt
bioblueprint-1.1.4.dist-info/RECORD
