Metadata-Version: 2.4
Name: bioblueprint
Version: 1.1.4
Summary: A workflow depedency graph compiler and pre-automation handler
Author-email: Zachary Konkel <zachary.konkel@theiagen.com>, Theron James <theron.james@theiagen.com>
License:                     GNU GENERAL PUBLIC LICENSE
Project-URL: Homepage, https://github.com/theiagen/bioblueprint
Project-URL: Bug Tracker, https://github.com/theiagen/bioblueprint/issues
Classifier: Programming Language :: Python :: 3
Classifier: License :: OSI Approved :: GNU Lesser General Public License v3 or later (LGPLv3+)
Classifier: Operating System :: POSIX :: Linux
Requires-Python: <4,>=3.0
License-File: LICENSE
Requires-Dist: PyYAML
Requires-Dist: miniwdl
Requires-Dist: matplotlib
Requires-Dist: networkx
Requires-Dist: gitpython
Dynamic: license-file
